stacksmith/__init__.py
stacksmith/api.py
stacksmith/cli.py
stacksmith/helpers.py
stacksmith-0.1.7.dist-info/LICENSE
stacksmith-0.1.7.dist-info/METADATA
stacksmith-0.1.7.dist-info/WHEEL
stacksmith-0.1.7.dist-info/entry_points.txt
stacksmith-0.1.7.dist-info/top_level.txt
stacksmith-0.1.7.dist-info/RECORD
