Metadata-Version: 2.1
Name: stacksmith
Version: 0.1.7
Summary: Enhanced Git workflow
Home-page: https://github.com/findjashua/stacksmith
Author: Jashua Gupta
Author-email: findjashua@gmail.com
Classifier: Development Status :: 3 - Alpha
Classifier: Intended Audience :: Developers
Classifier: License :: OSI Approved :: MIT License
Classifier: Operating System :: OS Independent
Classifier: Programming Language :: Python :: 3
Classifier: Programming Language :: Python :: 3.6
Classifier: Programming Language :: Python :: 3.7
Classifier: Programming Language :: Python :: 3.8
Classifier: Programming Language :: Python :: 3.9
Requires-Python: >=3.6
License-File: LICENSE
